pathfinder/Pathfinder.py
pathfinder/__init__.py
pathfinder/converter/EdgeExtractorFromPloverDB.py
pathfinder/converter/GraphToKnowledgeGraphConverter.py
pathfinder/converter/PathConverter.py
pathfinder/converter/PathListToGraphConverter.py
pathfinder/converter/ResultPerPathConverter.py
pathfinder/converter/__init__.py
pathfinder/core/BidirectionalPathFinder.py
pathfinder/core/BreadthFirstSearch.py
pathfinder/core/__init__.py
pathfinder/core/feature_extractor.py
pathfinder/core/model/Node.py
pathfinder/core/model/Path.py
pathfinder/core/model/PathContainer.py
pathfinder/core/model/PathFinderModel.py
pathfinder/core/model/__init__.py
pathfinder/core/repo/MLRepo.py
pathfinder/core/repo/MysqlNGDRepository.py
pathfinder/core/repo/MysqlNodeDegreeRepo.py
pathfinder/core/repo/NGDCalculator.py
pathfinder/core/repo/NGDRepository.py
pathfinder/core/repo/NGDSortedNeighborsRepo.py
pathfinder/core/repo/NodeDegreeRepo.py
pathfinder/core/repo/PloverDBRepo.py
pathfinder/core/repo/Repository.py
pathfinder/core/repo/__init__.py
pathfinder/core/repo/mysql_config_utility.py
pathfinder/core/repo/repo_factory.py
pathfinder/resources/__init__.py
pathfinder/resources/ancestors_by_indices.pkl
pathfinder/resources/edge_category_to_idx.pkl
pathfinder/resources/node_degree_category_by_indices.pkl
pathfinder/resources/pathfinder_xgboost_model_kg_2_10_2
pathfinder/resources/sorted_category_list.pkl
catrax_pathfinder-1.1.1.dist-info/METADATA
catrax_pathfinder-1.1.1.dist-info/WHEEL
catrax_pathfinder-1.1.1.dist-info/top_level.txt
catrax_pathfinder-1.1.1.dist-info/RECORD
