Metadata-Version: 2.4
Name: catrax-pathfinder
Version: 1.1.1
Summary: Pathfinder is designed to identify semantic paths between two biological entities.
Author-email: Mohsen Taheri <mohsen.taheri.1989@gmail.com>
License: MIT
Project-URL: Homepage, https://github.com/Translator-CATRAX/pathfinder
Project-URL: Issues, https://github.com/Translator-CATRAX/pathfinder/issues
Classifier: Programming Language :: Python :: 3
Classifier: Programming Language :: Python :: 3.9
Classifier: License :: OSI Approved :: MIT License
Classifier: Operating System :: OS Independent
Requires-Python: >=3.9
Requires-Dist: numpy==1.26.4
Requires-Dist: xgboost==2.1.4
Requires-Dist: pandas==2.3.1
Requires-Dist: mysql-connector-python
Requires-Dist: seaborn
Requires-Dist: matplotlib
Requires-Dist: optuna
